LICENSE
MANIFEST.in
README.md
setup.py
allauth_theme/__init__.py
allauth_theme/app_settings.py
allauth_theme/context_processors.py
allauth_theme/forms.py
allauth_theme/urls.py
allauth_theme/views.py
allauth_theme/static/css/signup.css
allauth_theme/static/css/tailwind.css
allauth_theme/static/img/google.png
allauth_theme/templates/allauth/account/account_inactive.html
allauth_theme/templates/allauth/account/base.html
allauth_theme/templates/allauth/account/email.html
allauth_theme/templates/allauth/account/email_confirm.html
allauth_theme/templates/allauth/account/login.html
allauth_theme/templates/allauth/account/logout.html
allauth_theme/templates/allauth/account/password_change.html
allauth_theme/templates/allauth/account/password_reset.html
allauth_theme/templates/allauth/account/password_reset_done.html
allauth_theme/templates/allauth/account/password_reset_from_key.html
allauth_theme/templates/allauth/account/password_reset_from_key_done.html
allauth_theme/templates/allauth/account/password_set.html
allauth_theme/templates/allauth/account/signup.html
allauth_theme/templates/allauth/account/signup_closed.html
allauth_theme/templates/allauth/account/verification_sent.html
allauth_theme/templates/allauth/account/verified_email_required.html
allauth_theme/templates/allauth/openid/base.html
allauth_theme/templates/allauth/openid/login.html
allauth_theme/templates/allauth/socialaccount/authentication_error.html
allauth_theme/templates/allauth/socialaccount/base.html
allauth_theme/templates/allauth/socialaccount/connections.html
allauth_theme/templates/allauth/socialaccount/login.html
allauth_theme/templates/allauth/socialaccount/login_cancelled.html
allauth_theme/templates/allauth/socialaccount/signup.html
allauth_theme/templates/allauth/socialaccount/snippets/provider_list.html
django_allauth_theme.egg-info/PKG-INFO
django_allauth_theme.egg-info/SOURCES.txt
django_allauth_theme.egg-info/dependency_links.txt
django_allauth_theme.egg-info/requires.txt
django_allauth_theme.egg-info/top_level.txt