Metadata-Version: 2.1
Name: django-allauth-theme
Version: 0.7.1
Summary: An awesome and responsive django-allauth theme based on tailwind
Home-page: http://pypi.python.org/pypi/django-allauth-theme/
Author: Leonardo Di Lella
Author-email: leonardo.dilella@mobileapart.com
License: LICENSE
Keywords: django auth account social openid twitter facebook oauth registration theme tailwindcss
Classifier: Development Status :: 5 - Production/Stable
Classifier: Intended Audience :: Developers
Classifier: Topic :: Software Development :: Libraries :: Python Modules
Classifier: Environment :: Web Environment
Classifier: Topic :: Internet
Classifier: License :: OSI Approved :: MIT License
Classifier: Operating System :: OS Independent
Classifier: Programming Language :: Python
Classifier: Programming Language :: Python :: 3
Classifier: Programming Language :: Python :: 3.5
Classifier: Programming Language :: Python :: 3.6
Classifier: Programming Language :: Python :: 3.7
Classifier: Programming Language :: Python :: 3.8
Classifier: Programming Language :: Python :: 3.9
Classifier: Programming Language :: Python :: 3.10
Classifier: Framework :: Django
Classifier: Framework :: Django :: 2.0
Classifier: Framework :: Django :: 2.1
Classifier: Framework :: Django :: 2.2
Classifier: Framework :: Django :: 3.0
Classifier: Framework :: Django :: 3.1
Classifier: Framework :: Django :: 3.2
Classifier: Framework :: Django :: 4.0
Classifier: Framework :: Django :: 4.1
Requires-Python: >=3.5
License-File: LICENSE
Requires-Dist: Django>=2.0
Requires-Dist: django-allauth>=0.51.0
Requires-Dist: django-crispy-forms>=1.14.0
